odoo8_addon_delivery_carrier_b2c-8.0.0.2.1-py3.8-nspkg.pth
odoo_addons/delivery_carrier_b2c/README.rst
odoo_addons/delivery_carrier_b2c/__init__.py
odoo_addons/delivery_carrier_b2c/__openerp__.py
odoo_addons/delivery_carrier_b2c/partner.py
odoo_addons/delivery_carrier_b2c/partner_view.xml
odoo_addons/delivery_carrier_b2c/i18n/am.po
odoo_addons/delivery_carrier_b2c/i18n/ar.po
odoo_addons/delivery_carrier_b2c/i18n/bg.po
odoo_addons/delivery_carrier_b2c/i18n/bs.po
odoo_addons/delivery_carrier_b2c/i18n/ca.po
odoo_addons/delivery_carrier_b2c/i18n/cs.po
odoo_addons/delivery_carrier_b2c/i18n/da.po
odoo_addons/delivery_carrier_b2c/i18n/de.po
odoo_addons/delivery_carrier_b2c/i18n/delivery_carrier_b2c.pot
odoo_addons/delivery_carrier_b2c/i18n/el_GR.po
odoo_addons/delivery_carrier_b2c/i18n/en_GB.po
odoo_addons/delivery_carrier_b2c/i18n/es.po
odoo_addons/delivery_carrier_b2c/i18n/es_CR.po
odoo_addons/delivery_carrier_b2c/i18n/es_EC.po
odoo_addons/delivery_carrier_b2c/i18n/es_MX.po
odoo_addons/delivery_carrier_b2c/i18n/es_VE.po
odoo_addons/delivery_carrier_b2c/i18n/et.po
odoo_addons/delivery_carrier_b2c/i18n/eu.po
odoo_addons/delivery_carrier_b2c/i18n/fi.po
odoo_addons/delivery_carrier_b2c/i18n/fr.po
odoo_addons/delivery_carrier_b2c/i18n/fr_CA.po
odoo_addons/delivery_carrier_b2c/i18n/fr_CH.po
odoo_addons/delivery_carrier_b2c/i18n/gl.po
odoo_addons/delivery_carrier_b2c/i18n/hr.po
odoo_addons/delivery_carrier_b2c/i18n/hr_HR.po
odoo_addons/delivery_carrier_b2c/i18n/hu.po
odoo_addons/delivery_carrier_b2c/i18n/id.po
odoo_addons/delivery_carrier_b2c/i18n/it.po
odoo_addons/delivery_carrier_b2c/i18n/ja.po
odoo_addons/delivery_carrier_b2c/i18n/lt.po
odoo_addons/delivery_carrier_b2c/i18n/lv.po
odoo_addons/delivery_carrier_b2c/i18n/mk.po
odoo_addons/delivery_carrier_b2c/i18n/mn.po
odoo_addons/delivery_carrier_b2c/i18n/nb.po
odoo_addons/delivery_carrier_b2c/i18n/nb_NO.po
odoo_addons/delivery_carrier_b2c/i18n/nl.po
odoo_addons/delivery_carrier_b2c/i18n/nl_BE.po
odoo8_addon_delivery_carrier_b2c-8.0.0.2.1.dist-info/METADATA
odoo8_addon_delivery_carrier_b2c-8.0.0.2.1.dist-info/WHEEL
odoo8_addon_delivery_carrier_b2c-8.0.0.2.1.dist-info/namespace_packages.txt
odoo8_addon_delivery_carrier_b2c-8.0.0.2.1.dist-info/top_level.txt
odoo8_addon_delivery_carrier_b2c-8.0.0.2.1.dist-info/RECORD
